soe_vinorm/__init__.py
soe_vinorm/cli.py
soe_vinorm/constants.py
soe_vinorm/normalizer.py
soe_vinorm/nsw_detector.py
soe_vinorm/nsw_expander.py
soe_vinorm/text_processor.py
soe_vinorm/utils.py
soe_vinorm/data/dictionaries/abbreviations.txt
soe_vinorm/data/dictionaries/vietnamese-syllables.txt
soe_vinorm-0.3.2.dist-info/METADATA
soe_vinorm-0.3.2.dist-info/WHEEL
soe_vinorm-0.3.2.dist-info/entry_points.txt
soe_vinorm-0.3.2.dist-info/licenses/LICENSE
soe_vinorm-0.3.2.dist-info/RECORD
