Metadata-Version: 2.4
Name: soe-vinorm
Version: 0.3.2
Summary: An effective text normalization tool for Vietnamese
Project-URL: Homepage, https://github.com/vinhdq842/soe-vinorm
Project-URL: Documentation, https://github.com/vinhdq842/soe-vinorm
Project-URL: Issues, https://github.com/vinhdq842/soe-vinorm/issues
Project-URL: Source Code, https://github.com/vinhdq842/soe-vinorm
Author-email: Vinh Dang <vinhdq842@gmail.com>
License-Expression: MIT
License-File: LICENSE
Keywords: nlp,non-standard-words,speech,text-normalization,tts,vietnamese
Classifier: Development Status :: 4 - Beta
Classifier: Intended Audience :: Developers
Classifier: License :: OSI Approved :: MIT License
Classifier: Natural Language :: Vietnamese
Classifier: Programming Language :: Python :: 3.8
Classifier: Programming Language :: Python :: 3.9
Classifier: Programming Language :: Python :: 3.10
Classifier: Programming Language :: Python :: 3.11
Classifier: Programming Language :: Python :: 3.12
Classifier: Topic :: Scientific/Engineering :: Artificial Intelligence
Classifier: Topic :: Text Processing
Classifier: Topic :: Text Processing :: Linguistic
Requires-Python: >=3.8
Requires-Dist: huggingface-hub<1.0.0,>=0.33.0
Requires-Dist: numpy<2.0.0,>=1.20.0
Requires-Dist: onnxruntime<1.20.0,>=1.16.0
Requires-Dist: sklearn-crfsuite<1.0.0,>=0.5.0
Requires-Dist: unidecode<2.0.0,>=1.3.0
